[{"status": "sleeping", "cpu_percent": 0.0, "uids": {"real": 9182, "effetive": 9182, "saved": 9182}, "gids": {"real": 32264, "effetive": 32264, "saved": 32264}, "ionice": {"ioclass": "IOPRIO_CLASS_NONE", "value": 4}, "cpu_num": 4, "pid": 427485, "num_threads": 7, "cmdline": ["singularity", "pull", "--force", "docker://alpine"], "create_time": 1558213302.57, "open_files": 0, "exe": "/usr/bin/singularity", "name": "singularity", "cpu_times": {"user": 0.0, "system": 0.0, "children_user": 0.0, "children_system": 0.0}, "memory_full_info": {"rss": 11788288, "vms": 321785856, "shared": 6795264, "text": 20971520, "lib": 0, "data": 288628736, "dirty": 0, "uss": 5062656, "pss": 7223296, "swap": 0}, "cwd": "/scratch/users/vsochat", "io_counters": {"read_count": 24, "write_count": 1, "read_bytes": 0, "write_bytes": 0, "read_chars": 19019, "write_chars": 36}, "num_ctx_switches": {"voluntary": 46, "involuntary": 42}, "nice": 0, "memory_percent": 0.00586036811623354, "username": "vsochat", "connections": [{"fd": 3, "family": "AddressFamily.AF_INET", "type": "SocketKind.SOCK_STREAM", "laddr_ip": "10.10.108.26", "laddr_port": 43384, "raddr": ["52.70.175.131", 443], "status": "SYN_SENT"}], "num_fds": 5, "cpu_affinity": [4], "ppid": 427469, "NPROC": "1", "HOSTNAME": "sh-108-26.int", "MAXMEMORY": "18", "SECONDS": "1"}, {"status": "sleeping", "cpu_percent": 0.0, "uids": {"real": 9182, "effetive": 9182, "saved": 9182}, "gids": {"real": 32264, "effetive": 32264, "saved": 32264}, "ionice": {"ioclass": "IOPRIO_CLASS_NONE", "value": 4}, "cpu_num": 4, "pid": 427485, "num_threads": 8, "cmdline": ["singularity", "pull", "--force", "docker://alpine"], "create_time": 1558213302.57, "open_files": 0, "exe": "/usr/bin/singularity", "name": "singularity", "cpu_times": {"user": 0.04, "system": 0.0, "children_user": 0.0, "children_system": 0.0}, "memory_full_info": {"rss": 15024128, "vms": 533012480, "shared": 7680000, "text": 20971520, "lib": 0, "data": 499855360, "dirty": 0, "uss": 7462912, "pss": 10002432, "swap": 0}, "cwd": "/scratch/users/vsochat", "io_counters": {"read_count": 78, "write_count": 16, "read_bytes": 4096, "write_bytes": 0, "read_chars": 734137, "write_chars": 4333}, "num_ctx_switches": {"voluntary": 46, "involuntary": 42}, "nice": 0, "memory_percent": 0.007469016765234406, "username": "vsochat", "connections": [{"fd": 3, "family": "AddressFamily.AF_INET", "type": "SocketKind.SOCK_STREAM", "laddr_ip": "10.10.108.26", "laddr_port": 43404, "raddr": ["52.70.175.131", 443], "status": "ESTABLISHED"}], "num_fds": 5, "cpu_affinity": [4], "ppid": 427469, "NPROC": "1", "HOSTNAME": "sh-108-26.int", "MAXMEMORY": "18", "SECONDS": "1"}, {"status": "sleeping", "cpu_percent": 0.0, "uids": {"real": 9182, "effetive": 9182, "saved": 9182}, "gids": {"real": 32264, "effetive": 32264, "saved": 32264}, "ionice": {"ioclass": "IOPRIO_CLASS_NONE", "value": 4}, "cpu_num": 4, "pid": 427485, "num_threads": 8, "cmdline": ["singularity", "pull", "--force", "docker://alpine"], "create_time": 1558213302.57, "open_files": 0, "exe": "/usr/bin/singularity", "name": "singularity", "cpu_times": {"user": 0.05, "system": 0.0, "children_user": 0.0, "children_system": 0.0}, "memory_full_info": {"rss": 15286272, "vms": 533012480, "shared": 7835648, "text": 20971520, "lib": 0, "data": 499855360, "dirty": 0, "uss": 7532544, "pss": 10112000, "swap": 0}, "cwd": "/scratch/users/vsochat", "io_counters": {"read_count": 113, "write_count": 35, "read_bytes": 4096, "write_bytes": 0, "read_chars": 758251, "write_chars": 11375}, "num_ctx_switches": {"voluntary": 46, "involuntary": 42}, "nice": 0, "memory_percent": 0.007599337668444604, "username": "vsochat", "connections": [{"fd": 3, "family": "AddressFamily.AF_INET", "type": "SocketKind.SOCK_STREAM", "laddr_ip": "10.10.108.26", "laddr_port": 43424, "raddr": ["52.70.175.131", 443], "status": "ESTABLISHED"}], "num_fds": 5, "cpu_affinity": [4], "ppid": 427469, "NPROC": "1", "HOSTNAME": "sh-108-26.int", "MAXMEMORY": "18", "SECONDS": "1"}, {"status": "sleeping", "cpu_percent": 0.0, "uids": {"real": 9182, "effetive": 9182, "saved": 9182}, "gids": {"real": 32264, "effetive": 32264, "saved": 32264}, "ionice": {"ioclass": "IOPRIO_CLASS_NONE", "value": 4}, "cpu_num": 4, "pid": 427485, "num_threads": 8, "cmdline": ["singularity", "pull", "--force", "docker://alpine"], "create_time": 1558213302.57, "open_files": 0, "exe": "/usr/bin/singularity", "name": "singularity", "cpu_times": {"user": 0.19, "system": 0.03, "children_user": 0.0, "children_system": 0.0}, "memory_full_info": {"rss": 19488768, "vms": 533012480, "shared": 8818688, "text": 20971520, "lib": 0, "data": 499855360, "dirty": 0, "uss": 10985472, "pss": 15162368, "swap": 0}, "cwd": "/scratch/users/vsochat", "io_counters": {"read_count": 994, "write_count": 407, "read_bytes": 2789376, "write_bytes": 8581120, "read_chars": 9059600, "write_chars": 8313562}, "num_ctx_switches": {"voluntary": 46, "involuntary": 42}, "nice": 0, "memory_percent": 0.009688544648033072, "username": "vsochat", "connections": [], "num_fds": 5, "cpu_affinity": [4], "ppid": 427469, "NPROC": "1", "HOSTNAME": "sh-108-26.int", "MAXMEMORY": "18", "SECONDS": "1"}]
