[{"username": "vsochat", "name": "singularity", "cpu_times": {"user": 0.01, "system": 0.0, "children_user": 0.0, "children_system": 0.0}, "status": "sleeping", "create_time": 1558213468.0, "gids": {"real": 32264, "effetive": 32264, "saved": 32264}, "uids": {"real": 9182, "effetive": 9182, "saved": 9182}, "ionice": {"ioclass": "IOPRIO_CLASS_NONE", "value": 4}, "num_ctx_switches": {"voluntary": 53, "involuntary": 7}, "open_files": 0, "cmdline": ["singularity", "pull", "--force", "docker://alpine"], "cpu_num": 6, "connections": [{"fd": 3, "family": "AddressFamily.AF_INET", "type": "SocketKind.SOCK_STREAM", "laddr_ip": "10.10.17.2", "laddr_port": 43140, "raddr": ["34.232.31.24", 443], "status": "SYN_SENT"}], "ppid": 121047, "cwd": "/scratch/users/vsochat", "num_threads": 8, "io_counters": {"read_count": 23, "write_count": 1, "read_bytes": 0, "write_bytes": 0, "read_chars": 13402, "write_chars": 36}, "pid": 121054, "cpu_affinity": [6], "num_fds": 5, "memory_full_info": {"rss": 11653120, "vms": 396713984, "shared": 6754304, "text": 20971520, "lib": 0, "data": 364130304, "dirty": 0, "uss": 4976640, "pss": 8195072, "swap": 0}, "exe": "/usr/bin/singularity", "memory_percent": 0.01735986001301776, "cpu_percent": 0.0, "nice": 0, "NPROC": "1", "HOSTNAME": "sh-17-02.int", "MAXMEMORY": "4", "SECONDS": "1"}, {"username": "vsochat", "name": "singularity", "cpu_times": {"user": 0.07, "system": 0.01, "children_user": 0.0, "children_system": 0.0}, "status": "sleeping", "create_time": 1558213468.0, "gids": {"real": 32264, "effetive": 32264, "saved": 32264}, "uids": {"real": 9182, "effetive": 9182, "saved": 9182}, "ionice": {"ioclass": "IOPRIO_CLASS_NONE", "value": 4}, "num_ctx_switches": {"voluntary": 53, "involuntary": 7}, "open_files": 0, "cmdline": ["singularity", "pull", "--force", "docker://alpine"], "cpu_num": 6, "connections": [{"fd": 3, "family": "AddressFamily.AF_INET", "type": "SocketKind.SOCK_STREAM", "laddr_ip": "10.10.17.2", "laddr_port": 43154, "raddr": ["34.232.31.24", 443], "status": "ESTABLISHED"}], "ppid": 121047, "cwd": "/scratch/users/vsochat", "num_threads": 8, "io_counters": {"read_count": 75, "write_count": 16, "read_bytes": 4096, "write_bytes": 0, "read_chars": 728920, "write_chars": 4333}, "pid": 121054, "cpu_affinity": [6], "num_fds": 5, "memory_full_info": {"rss": 14946304, "vms": 532439040, "shared": 7786496, "text": 20971520, "lib": 0, "data": 499855360, "dirty": 0, "uss": 7282688, "pss": 11062272, "swap": 0}, "exe": "/usr/bin/singularity", "memory_percent": 0.02226577475834861, "cpu_percent": 0.0, "nice": 0, "NPROC": "1", "HOSTNAME": "sh-17-02.int", "MAXMEMORY": "4", "SECONDS": "1"}, {"username": "vsochat", "name": "singularity", "cpu_times": {"user": 0.09, "system": 0.01, "children_user": 0.0, "children_system": 0.0}, "status": "sleeping", "create_time": 1558213468.0, "gids": {"real": 32264, "effetive": 32264, "saved": 32264}, "uids": {"real": 9182, "effetive": 9182, "saved": 9182}, "ionice": {"ioclass": "IOPRIO_CLASS_NONE", "value": 4}, "num_ctx_switches": {"voluntary": 53, "involuntary": 7}, "open_files": 0, "cmdline": ["singularity", "pull", "--force", "docker://alpine"], "cpu_num": 6, "connections": [{"fd": 3, "family": "AddressFamily.AF_INET", "type": "SocketKind.SOCK_STREAM", "laddr_ip": "10.10.17.2", "laddr_port": 43168, "raddr": ["34.232.31.24", 443], "status": "SYN_SENT"}], "ppid": 121047, "cwd": "/scratch/users/vsochat", "num_threads": 8, "io_counters": {"read_count": 107, "write_count": 34, "read_bytes": 4096, "write_bytes": 0, "read_chars": 753035, "write_chars": 11216}, "pid": 121054, "cpu_affinity": [6], "num_fds": 5, "memory_full_info": {"rss": 14946304, "vms": 599547904, "shared": 7786496, "text": 20971520, "lib": 0, "data": 566964224, "dirty": 0, "uss": 7426048, "pss": 11213824, "swap": 0}, "exe": "/usr/bin/singularity", "memory_percent": 0.02226577475834861, "cpu_percent": 0.0, "nice": 0, "NPROC": "1", "HOSTNAME": "sh-17-02.int", "MAXMEMORY": "4", "SECONDS": "1"}, {"username": "vsochat", "name": "singularity", "cpu_times": {"user": 0.3, "system": 0.05, "children_user": 0.0, "children_system": 0.0}, "status": "sleeping", "create_time": 1558213468.0, "gids": {"real": 32264, "effetive": 32264, "saved": 32264}, "uids": {"real": 9182, "effetive": 9182, "saved": 9182}, "ionice": {"ioclass": "IOPRIO_CLASS_NONE", "value": 4}, "num_ctx_switches": {"voluntary": 53, "involuntary": 7}, "open_files": 0, "cmdline": ["singularity", "pull", "--force", "docker://alpine"], "cpu_num": 6, "connections": [], "ppid": 121047, "cwd": "/scratch/users/vsochat", "num_threads": 8, "io_counters": {"read_count": 989, "write_count": 407, "read_bytes": 2789376, "write_bytes": 8581120, "read_chars": 9055029, "write_chars": 8313885}, "pid": 121054, "cpu_affinity": [6], "num_fds": 5, "memory_full_info": {"rss": 18604032, "vms": 599547904, "shared": 8638464, "text": 20971520, "lib": 0, "data": 566964224, "dirty": 0, "uss": 18501632, "pss": 18580480, "swap": 0}, "exe": "/usr/bin/singularity", "memory_percent": 0.02771475718071236, "cpu_percent": 0.0, "nice": 0, "NPROC": "1", "HOSTNAME": "sh-17-02.int", "MAXMEMORY": "4", "SECONDS": "1"}]
