[{"connections": [{"fd": 3, "family": "AddressFamily.AF_INET", "type": "SocketKind.SOCK_STREAM", "laddr_ip": "10.10.107.18", "laddr_port": 58608, "raddr": ["34.197.189.129", 443], "status": "SYN_SENT"}], "open_files": 0, "ppid": 341654, "io_counters": {"read_count": 24, "write_count": 1, "read_bytes": 0, "write_bytes": 0, "read_chars": 19098, "write_chars": 36}, "status": "sleeping", "num_ctx_switches": {"voluntary": 58, "involuntary": 2}, "username": "vsochat", "num_fds": 5, "cpu_times": {"user": 0.0, "system": 0.01, "children_user": 0.0, "children_system": 0.0}, "cpu_percent": 0.0, "nice": 0, "create_time": 1558213465.56, "ionice": {"ioclass": "IOPRIO_CLASS_NONE", "value": 4}, "memory_percent": 0.005848150531557583, "pid": 341657, "memory_full_info": {"rss": 11763712, "vms": 474181632, "shared": 6672384, "text": 20971520, "lib": 0, "data": 441597952, "dirty": 0, "uss": 11755520, "pss": 11770880, "swap": 0}, "exe": "/usr/bin/singularity", "cmdline": ["singularity", "pull", "--force", "docker://nginx"], "cpu_num": 2, "gids": {"real": 32264, "effetive": 32264, "saved": 32264}, "cwd": "/scratch/users/vsochat", "num_threads": 9, "name": "singularity", "cpu_affinity": [0, 1, 2], "uids": {"real": 9182, "effetive": 9182, "saved": 9182}, "NPROC": "1", "HOSTNAME": "sh-107-18.int", "MAXMEMORY": "128", "SECONDS": "1"}, {"connections": [{"fd": 3, "family": "AddressFamily.AF_INET", "type": "SocketKind.SOCK_STREAM", "laddr_ip": "10.10.107.18", "laddr_port": 58614, "raddr": ["34.197.189.129", 443], "status": "ESTABLISHED"}], "open_files": 0, "ppid": 341654, "io_counters": {"read_count": 76, "write_count": 17, "read_bytes": 4096, "write_bytes": 0, "read_chars": 734360, "write_chars": 4529}, "status": "sleeping", "num_ctx_switches": {"voluntary": 58, "involuntary": 2}, "username": "vsochat", "num_fds": 5, "cpu_times": {"user": 0.04, "system": 0.01, "children_user": 0.0, "children_system": 0.0}, "cpu_percent": 0.0, "nice": 0, "create_time": 1558213465.56, "ionice": {"ioclass": "IOPRIO_CLASS_NONE", "value": 4}, "memory_percent": 0.007798891551485217, "pid": 341657, "memory_full_info": {"rss": 15687680, "vms": 491032576, "shared": 7692288, "text": 20971520, "lib": 0, "data": 458448896, "dirty": 0, "uss": 15785984, "pss": 15801344, "swap": 0}, "exe": "/usr/bin/singularity", "cmdline": ["singularity", "pull", "--force", "docker://nginx"], "cpu_num": 2, "gids": {"real": 32264, "effetive": 32264, "saved": 32264}, "cwd": "/scratch/users/vsochat", "num_threads": 11, "name": "singularity", "cpu_affinity": [0, 1, 2], "uids": {"real": 9182, "effetive": 9182, "saved": 9182}, "NPROC": "1", "HOSTNAME": "sh-107-18.int", "MAXMEMORY": "128", "SECONDS": "1"}, {"connections": [{"fd": 3, "family": "AddressFamily.AF_INET", "type": "SocketKind.SOCK_STREAM", "laddr_ip": "10.10.107.18", "laddr_port": 58622, "raddr": ["34.197.189.129", 443], "status": "ESTABLISHED"}], "open_files": 0, "ppid": 341654, "io_counters": {"read_count": 115, "write_count": 38, "read_bytes": 4096, "write_bytes": 0, "read_chars": 763892, "write_chars": 11697}, "status": "sleeping", "num_ctx_switches": {"voluntary": 58, "involuntary": 2}, "username": "vsochat", "num_fds": 5, "cpu_times": {"user": 0.04, "system": 0.02, "children_user": 0.0, "children_system": 0.0}, "cpu_percent": 0.0, "nice": 0, "create_time": 1558213465.56, "ionice": {"ioclass": "IOPRIO_CLASS_NONE", "value": 4}, "memory_percent": 0.007798891551485217, "pid": 341657, "memory_full_info": {"rss": 15687680, "vms": 625250304, "shared": 7692288, "text": 20971520, "lib": 0, "data": 592666624, "dirty": 0, "uss": 15994880, "pss": 16010240, "swap": 0}, "exe": "/usr/bin/singularity", "cmdline": ["singularity", "pull", "--force", "docker://nginx"], "cpu_num": 2, "gids": {"real": 32264, "effetive": 32264, "saved": 32264}, "cwd": "/scratch/users/vsochat", "num_threads": 11, "name": "singularity", "cpu_affinity": [0, 1, 2], "uids": {"real": 9182, "effetive": 9182, "saved": 9182}, "NPROC": "1", "HOSTNAME": "sh-107-18.int", "MAXMEMORY": "128", "SECONDS": "1"}, {"connections": [], "open_files": 2, "ppid": 341654, "io_counters": {"read_count": 3774, "write_count": 1887, "read_bytes": 44830720, "write_bytes": 53063680, "read_chars": 93914391, "write_chars": 52513062}, "status": "sleeping", "num_ctx_switches": {"voluntary": 58, "involuntary": 2}, "username": "vsochat", "num_fds": 6, "cpu_times": {"user": 0.59, "system": 0.11, "children_user": 0.0, "children_system": 0.0}, "cpu_percent": 0.0, "nice": 0, "create_time": 1558213465.56, "ionice": {"ioclass": "IOPRIO_CLASS_NONE", "value": 4}, "memory_percent": 0.010549884367687966, "pid": 341657, "memory_full_info": {"rss": 21221376, "vms": 625250304, "shared": 8454144, "text": 20971520, "lib": 0, "data": 592666624, "dirty": 0, "uss": 21467136, "pss": 21482496, "swap": 0}, "exe": "/usr/bin/singularity", "cmdline": ["singularity", "pull", "--force", "docker://nginx"], "cpu_num": 2, "gids": {"real": 32264, "effetive": 32264, "saved": 32264}, "cwd": "/scratch/users/vsochat", "num_threads": 11, "name": "singularity", "cpu_affinity": [0, 1, 2], "uids": {"real": 9182, "effetive": 9182, "saved": 9182}, "NPROC": "1", "HOSTNAME": "sh-107-18.int", "MAXMEMORY": "128", "SECONDS": "1"}, {"connections": [], "open_files": 2, "ppid": 341654, "io_counters": {"read_count": 11706, "write_count": 7045, "read_bytes": 44830720, "write_bytes": 138821632, "read_chars": 126452534, "write_chars": 131163101}, "status": "sleeping", "num_ctx_switches": {"voluntary": 58, "involuntary": 2}, "username": "vsochat", "num_fds": 6, "cpu_times": {"user": 1.52, "system": 0.26, "children_user": 0.0, "children_system": 0.0}, "cpu_percent": 0.0, "nice": 0, "create_time": 1558213465.56, "ionice": {"ioclass": "IOPRIO_CLASS_NONE", "value": 4}, "memory_percent": 0.010743329458390603, "pid": 341657, "memory_full_info": {"rss": 21610496, "vms": 625250304, "shared": 8736768, "text": 20971520, "lib": 0, "data": 592666624, "dirty": 0, "uss": 21549056, "pss": 21564416, "swap": 0}, "exe": "/usr/bin/singularity", "cmdline": ["singularity", "pull", "--force", "docker://nginx"], "cpu_num": 2, "gids": {"real": 32264, "effetive": 32264, "saved": 32264}, "cwd": "/scratch/users/vsochat", "num_threads": 11, "name": "singularity", "cpu_affinity": [0, 1, 2], "uids": {"real": 9182, "effetive": 9182, "saved": 9182}, "NPROC": "1", "HOSTNAME": "sh-107-18.int", "MAXMEMORY": "128", "SECONDS": "1"}, {"connections": [], "open_files": 0, "ppid": 341654, "io_counters": {"read_count": 13842, "write_count": 8208, "read_bytes": 44879872, "write_bytes": 163229696, "read_chars": 135169585, "write_chars": 154135771}, "status": "sleeping", "num_ctx_switches": {"voluntary": 58, "involuntary": 2}, "username": "vsochat", "num_fds": 5, "cpu_times": {"user": 1.76, "system": 0.3, "children_user": 0.0, "children_system": 0.0}, "cpu_percent": 0.0, "nice": 0, "create_time": 1558213465.56, "ionice": {"ioclass": "IOPRIO_CLASS_NONE", "value": 4}, "memory_percent": 0.01093473828498058, "pid": 341657, "memory_full_info": {"rss": 21995520, "vms": 625250304, "shared": 8822784, "text": 20971520, "lib": 0, "data": 592666624, "dirty": 0, "uss": 22020096, "pss": 22035456, "swap": 0}, "exe": "/usr/bin/singularity", "cmdline": ["singularity", "pull", "--force", "docker://nginx"], "cpu_num": 2, "gids": {"real": 32264, "effetive": 32264, "saved": 32264}, "cwd": "/scratch/users/vsochat", "num_threads": 11, "name": "singularity", "cpu_affinity": [0, 1, 2], "uids": {"real": 9182, "effetive": 9182, "saved": 9182}, "NPROC": "1", "HOSTNAME": "sh-107-18.int", "MAXMEMORY": "128", "SECONDS": "1"}, {"connections": [], "open_files": 0, "ppid": 341654, "io_counters": {"read_count": 13842, "write_count": 8208, "read_bytes": 44879872, "write_bytes": 163229696, "read_chars": 135169585, "write_chars": 154135771}, "status": "sleeping", "num_ctx_switches": {"voluntary": 58, "involuntary": 2}, "username": "vsochat", "num_fds": 5, "cpu_times": {"user": 1.76, "system": 0.3, "children_user": 0.0, "children_system": 0.0}, "cpu_percent": 0.0, "nice": 0, "create_time": 1558213465.56, "ionice": {"ioclass": "IOPRIO_CLASS_NONE", "value": 4}, "memory_percent": 0.01093473828498058, "pid": 341657, "memory_full_info": {"rss": 21995520, "vms": 625250304, "shared": 8822784, "text": 20971520, "lib": 0, "data": 592666624, "dirty": 0, "uss": 22020096, "pss": 22035456, "swap": 0}, "exe": "/usr/bin/singularity", "cmdline": ["singularity", "pull", "--force", "docker://nginx"], "cpu_num": 2, "gids": {"real": 32264, "effetive": 32264, "saved": 32264}, "cwd": "/scratch/users/vsochat", "num_threads": 11, "name": "singularity", "cpu_affinity": [0, 1, 2], "uids": {"real": 9182, "effetive": 9182, "saved": 9182}, "NPROC": "1", "HOSTNAME": "sh-107-18.int", "MAXMEMORY": "128", "SECONDS": "1"}, {"connections": [], "open_files": 0, "ppid": 341654, "io_counters": {"read_count": 13842, "write_count": 8208, "read_bytes": 44879872, "write_bytes": 163229696, "read_chars": 135169585, "write_chars": 154135771}, "status": "sleeping", "num_ctx_switches": {"voluntary": 58, "involuntary": 2}, "username": "vsochat", "num_fds": 5, "cpu_times": {"user": 1.76, "system": 0.3, "children_user": 0.0, "children_system": 0.0}, "cpu_percent": 0.0, "nice": 0, "create_time": 1558213465.56, "ionice": {"ioclass": "IOPRIO_CLASS_NONE", "value": 4}, "memory_percent": 0.01093473828498058, "pid": 341657, "memory_full_info": {"rss": 21995520, "vms": 625250304, "shared": 8822784, "text": 20971520, "lib": 0, "data": 592666624, "dirty": 0, "uss": 22020096, "pss": 22035456, "swap": 0}, "exe": "/usr/bin/singularity", "cmdline": ["singularity", "pull", "--force", "docker://nginx"], "cpu_num": 2, "gids": {"real": 32264, "effetive": 32264, "saved": 32264}, "cwd": "/scratch/users/vsochat", "num_threads": 11, "name": "singularity", "cpu_affinity": [0, 1, 2], "uids": {"real": 9182, "effetive": 9182, "saved": 9182}, "NPROC": "1", "HOSTNAME": "sh-107-18.int", "MAXMEMORY": "128", "SECONDS": "1"}, {"connections": [], "open_files": 0, "ppid": 341654, "io_counters": {"read_count": 13842, "write_count": 8208, "read_bytes": 44879872, "write_bytes": 163229696, "read_chars": 135169585, "write_chars": 154135771}, "status": "sleeping", "num_ctx_switches": {"voluntary": 58, "involuntary": 2}, "username": "vsochat", "num_fds": 5, "cpu_times": {"user": 1.76, "system": 0.3, "children_user": 0.0, "children_system": 0.0}, "cpu_percent": 0.0, "nice": 0, "create_time": 1558213465.56, "ionice": {"ioclass": "IOPRIO_CLASS_NONE", "value": 4}, "memory_percent": 0.01093473828498058, "pid": 341657, "memory_full_info": {"rss": 21995520, "vms": 625250304, "shared": 8822784, "text": 20971520, "lib": 0, "data": 592666624, "dirty": 0, "uss": 22020096, "pss": 22034432, "swap": 0}, "exe": "/usr/bin/singularity", "cmdline": ["singularity", "pull", "--force", "docker://nginx"], "cpu_num": 2, "gids": {"real": 32264, "effetive": 32264, "saved": 32264}, "cwd": "/scratch/users/vsochat", "num_threads": 11, "name": "singularity", "cpu_affinity": [0, 1, 2], "uids": {"real": 9182, "effetive": 9182, "saved": 9182}, "NPROC": "1", "HOSTNAME": "sh-107-18.int", "MAXMEMORY": "128", "SECONDS": "1"}, {"connections": [], "open_files": 0, "ppid": 341654, "io_counters": {"read_count": 13842, "write_count": 8208, "read_bytes": 44879872, "write_bytes": 163229696, "read_chars": 135169585, "write_chars": 154135771}, "status": "sleeping", "num_ctx_switches": {"voluntary": 58, "involuntary": 2}, "username": "vsochat", "num_fds": 5, "cpu_times": {"user": 1.76, "system": 0.3, "children_user": 0.0, "children_system": 0.0}, "cpu_percent": 0.0, "nice": 0, "create_time": 1558213465.56, "ionice": {"ioclass": "IOPRIO_CLASS_NONE", "value": 4}, "memory_percent": 0.01093473828498058, "pid": 341657, "memory_full_info": {"rss": 21995520, "vms": 625250304, "shared": 8822784, "text": 20971520, "lib": 0, "data": 592666624, "dirty": 0, "uss": 22020096, "pss": 22035456, "swap": 0}, "exe": "/usr/bin/singularity", "cmdline": ["singularity", "pull", "--force", "docker://nginx"], "cpu_num": 2, "gids": {"real": 32264, "effetive": 32264, "saved": 32264}, "cwd": "/scratch/users/vsochat", "num_threads": 11, "name": "singularity", "cpu_affinity": [0, 1, 2], "uids": {"real": 9182, "effetive": 9182, "saved": 9182}, "NPROC": "1", "HOSTNAME": "sh-107-18.int", "MAXMEMORY": "128", "SECONDS": "1"}, {"connections": [], "open_files": 0, "ppid": 341654, "io_counters": {"read_count": 13842, "write_count": 8208, "read_bytes": 44879872, "write_bytes": 163229696, "read_chars": 135169585, "write_chars": 154135771}, "status": "sleeping", "num_ctx_switches": {"voluntary": 58, "involuntary": 2}, "username": "vsochat", "num_fds": 5, "cpu_times": {"user": 1.76, "system": 0.3, "children_user": 0.0, "children_system": 0.0}, "cpu_percent": 0.0, "nice": 0, "create_time": 1558213465.56, "ionice": {"ioclass": "IOPRIO_CLASS_NONE", "value": 4}, "memory_percent": 0.01093473828498058, "pid": 341657, "memory_full_info": {"rss": 21995520, "vms": 625250304, "shared": 8822784, "text": 20971520, "lib": 0, "data": 592666624, "dirty": 0, "uss": 22020096, "pss": 22035456, "swap": 0}, "exe": "/usr/bin/singularity", "cmdline": ["singularity", "pull", "--force", "docker://nginx"], "cpu_num": 2, "gids": {"real": 32264, "effetive": 32264, "saved": 32264}, "cwd": "/scratch/users/vsochat", "num_threads": 11, "name": "singularity", "cpu_affinity": [0, 1, 2], "uids": {"real": 9182, "effetive": 9182, "saved": 9182}, "NPROC": "1", "HOSTNAME": "sh-107-18.int", "MAXMEMORY": "128", "SECONDS": "1"}, {"connections": [], "open_files": 0, "ppid": 341654, "io_counters": {"read_count": 13842, "write_count": 8208, "read_bytes": 44879872, "write_bytes": 163229696, "read_chars": 135169585, "write_chars": 154135771}, "status": "sleeping", "num_ctx_switches": {"voluntary": 58, "involuntary": 2}, "username": "vsochat", "num_fds": 5, "cpu_times": {"user": 1.76, "system": 0.3, "children_user": 0.0, "children_system": 0.0}, "cpu_percent": 0.0, "nice": 0, "create_time": 1558213465.56, "ionice": {"ioclass": "IOPRIO_CLASS_NONE", "value": 4}, "memory_percent": 0.01093473828498058, "pid": 341657, "memory_full_info": {"rss": 21995520, "vms": 625250304, "shared": 8822784, "text": 20971520, "lib": 0, "data": 592666624, "dirty": 0, "uss": 22020096, "pss": 22035456, "swap": 0}, "exe": "/usr/bin/singularity", "cmdline": ["singularity", "pull", "--force", "docker://nginx"], "cpu_num": 2, "gids": {"real": 32264, "effetive": 32264, "saved": 32264}, "cwd": "/scratch/users/vsochat", "num_threads": 11, "name": "singularity", "cpu_affinity": [0, 1, 2], "uids": {"real": 9182, "effetive": 9182, "saved": 9182}, "NPROC": "1", "HOSTNAME": "sh-107-18.int", "MAXMEMORY": "128", "SECONDS": "1"}]
