[{"io_counters": {"read_count": 33, "write_count": 2, "read_bytes": 0, "write_bytes": 0, "read_chars": 442556, "write_chars": 195}, "pid": 16364, "status": "sleeping", "cpu_num": 15, "num_fds": 5, "ionice": {"ioclass": "IOPRIO_CLASS_NONE", "value": 4}, "exe": "/usr/bin/singularity", "ppid": 16360, "cpu_affinity": [15], "cmdline": ["singularity", "pull", "--force", "docker://nginx"], "gids": {"real": 32264, "effetive": 32264, "saved": 32264}, "create_time": 1558213399.68, "name": "singularity", "cpu_percent": 0.0, "uids": {"real": 9182, "effetive": 9182, "saved": 9182}, "num_ctx_switches": {"voluntary": 43, "involuntary": 43}, "num_threads": 7, "cwd": "/scratch/users/vsochat", "cpu_times": {"user": 0.04, "system": 0.01, "children_user": 0.0, "children_system": 0.0}, "username": "vsochat", "memory_percent": 0.019569352581092367, "memory_full_info": {"rss": 14503936, "vms": 457613312, "shared": 7749632, "text": 20971520, "lib": 0, "data": 424353792, "dirty": 0, "uss": 13017088, "pss": 13032448, "swap": 0}, "connections": [{"fd": 3, "family": "AddressFamily.AF_INET", "type": "SocketKind.SOCK_STREAM", "laddr_ip": "10.10.1.9", "laddr_port": 39594, "raddr": ["52.70.175.131", 443], "status": "ESTABLISHED"}], "nice": 0, "open_files": 0, "NPROC": "1", "HOSTNAME": "sh-01-09.int", "MAXMEMORY": "8", "SECONDS": "1"}, {"io_counters": {"read_count": 77, "write_count": 18, "read_bytes": 4096, "write_bytes": 0, "read_chars": 727193, "write_chars": 4560}, "pid": 16364, "status": "sleeping", "cpu_num": 15, "num_fds": 5, "ionice": {"ioclass": "IOPRIO_CLASS_NONE", "value": 4}, "exe": "/usr/bin/singularity", "ppid": 16360, "cpu_affinity": [15], "cmdline": ["singularity", "pull", "--force", "docker://nginx"], "gids": {"real": 32264, "effetive": 32264, "saved": 32264}, "create_time": 1558213399.68, "name": "singularity", "cpu_percent": 0.0, "uids": {"real": 9182, "effetive": 9182, "saved": 9182}, "num_ctx_switches": {"voluntary": 43, "involuntary": 43}, "num_threads": 8, "cwd": "/scratch/users/vsochat", "cpu_times": {"user": 0.08, "system": 0.01, "children_user": 0.0, "children_system": 0.0}, "username": "vsochat", "memory_percent": 0.02191743156657625, "memory_full_info": {"rss": 14757888, "vms": 600223744, "shared": 7839744, "text": 20971520, "lib": 0, "data": 566964224, "dirty": 0, "uss": 14741504, "pss": 14756864, "swap": 0}, "connections": [{"fd": 3, "family": "AddressFamily.AF_INET", "type": "SocketKind.SOCK_STREAM", "laddr_ip": "10.10.1.9", "laddr_port": 57970, "raddr": ["100.24.246.89", 443], "status": "SYN_SENT"}], "nice": 0, "open_files": 0, "NPROC": "1", "HOSTNAME": "sh-01-09.int", "MAXMEMORY": "8", "SECONDS": "1"}, {"io_counters": {"read_count": 115, "write_count": 40, "read_bytes": 4096, "write_bytes": 0, "read_chars": 756293, "write_chars": 14087}, "pid": 16364, "status": "sleeping", "cpu_num": 15, "num_fds": 5, "ionice": {"ioclass": "IOPRIO_CLASS_NONE", "value": 4}, "exe": "/usr/bin/singularity", "ppid": 16360, "cpu_affinity": [15], "cmdline": ["singularity", "pull", "--force", "docker://nginx"], "gids": {"real": 32264, "effetive": 32264, "saved": 32264}, "create_time": 1558213399.68, "name": "singularity", "cpu_percent": 0.0, "uids": {"real": 9182, "effetive": 9182, "saved": 9182}, "num_ctx_switches": {"voluntary": 43, "involuntary": 43}, "num_threads": 8, "cwd": "/scratch/users/vsochat", "cpu_times": {"user": 0.09, "system": 0.02, "children_user": 0.0, "children_system": 0.0}, "username": "vsochat", "memory_percent": 0.022665653626717488, "memory_full_info": {"rss": 15261696, "vms": 600223744, "shared": 8257536, "text": 20971520, "lib": 0, "data": 566964224, "dirty": 0, "uss": 14909440, "pss": 14924800, "swap": 0}, "connections": [{"fd": 3, "family": "AddressFamily.AF_INET", "type": "SocketKind.SOCK_STREAM", "laddr_ip": "10.10.1.9", "laddr_port": 39608, "raddr": ["52.70.175.131", 443], "status": "ESTABLISHED"}], "nice": 0, "open_files": 0, "NPROC": "1", "HOSTNAME": "sh-01-09.int", "MAXMEMORY": "8", "SECONDS": "1"}, {"io_counters": {"read_count": 1503, "write_count": 1426, "read_bytes": 44802048, "write_bytes": 44789760, "read_chars": 45557162, "write_chars": 44809539}, "pid": 16364, "status": "sleeping", "cpu_num": 15, "num_fds": 6, "ionice": {"ioclass": "IOPRIO_CLASS_NONE", "value": 4}, "exe": "/usr/bin/singularity", "ppid": 16360, "cpu_affinity": [15], "cmdline": ["singularity", "pull", "--force", "docker://nginx"], "gids": {"real": 32264, "effetive": 32264, "saved": 32264}, "create_time": 1558213399.68, "name": "singularity", "cpu_percent": 0.0, "uids": {"real": 9182, "effetive": 9182, "saved": 9182}, "num_ctx_switches": {"voluntary": 43, "involuntary": 43}, "num_threads": 8, "cwd": "/scratch/users/vsochat", "cpu_times": {"user": 0.69, "system": 0.09, "children_user": 0.0, "children_system": 0.0}, "username": "vsochat", "memory_percent": 0.03048244506803042, "memory_full_info": {"rss": 20525056, "vms": 600223744, "shared": 8368128, "text": 20971520, "lib": 0, "data": 566964224, "dirty": 0, "uss": 20389888, "pss": 20405248, "swap": 0}, "connections": [], "nice": 0, "open_files": 0, "NPROC": "1", "HOSTNAME": "sh-01-09.int", "MAXMEMORY": "8", "SECONDS": "1"}, {"io_counters": {"read_count": 7863, "write_count": 4244, "read_bytes": 44830720, "write_bytes": 95289344, "read_chars": 110671668, "write_chars": 92170889}, "pid": 16364, "status": "sleeping", "cpu_num": 15, "num_fds": 6, "ionice": {"ioclass": "IOPRIO_CLASS_NONE", "value": 4}, "exe": "/usr/bin/singularity", "ppid": 16360, "cpu_affinity": [15], "cmdline": ["singularity", "pull", "--force", "docker://nginx"], "gids": {"real": 32264, "effetive": 32264, "saved": 32264}, "create_time": 1558213399.68, "name": "singularity", "cpu_percent": 0.0, "uids": {"real": 9182, "effetive": 9182, "saved": 9182}, "num_ctx_switches": {"voluntary": 43, "involuntary": 43}, "num_threads": 8, "cwd": "/scratch/users/vsochat", "cpu_times": {"user": 1.56, "system": 0.2, "children_user": 0.0, "children_system": 0.0}, "username": "vsochat", "memory_percent": 0.03350574883949542, "memory_full_info": {"rss": 22560768, "vms": 600223744, "shared": 8970240, "text": 20971520, "lib": 0, "data": 566964224, "dirty": 0, "uss": 22261760, "pss": 22277120, "swap": 0}, "connections": [], "nice": 0, "open_files": 2, "NPROC": "1", "HOSTNAME": "sh-01-09.int", "MAXMEMORY": "8", "SECONDS": "1"}, {"io_counters": {"read_count": 13828, "write_count": 8204, "read_bytes": 44830720, "write_bytes": 163221504, "read_chars": 135150786, "write_chars": 154135398}, "pid": 16364, "status": "sleeping", "cpu_num": 15, "num_fds": 5, "ionice": {"ioclass": "IOPRIO_CLASS_NONE", "value": 4}, "exe": "/usr/bin/singularity", "ppid": 16360, "cpu_affinity": [15], "cmdline": ["singularity", "pull", "--force", "docker://nginx"], "gids": {"real": 32264, "effetive": 32264, "saved": 32264}, "create_time": 1558213399.68, "name": "singularity", "cpu_percent": 0.0, "uids": {"real": 9182, "effetive": 9182, "saved": 9182}, "num_ctx_switches": {"voluntary": 43, "involuntary": 43}, "num_threads": 8, "cwd": "/scratch/users/vsochat", "cpu_times": {"user": 2.25, "system": 0.35, "children_user": 0.0, "children_system": 0.0}, "username": "vsochat", "memory_percent": 0.047472560628798524, "memory_full_info": {"rss": 31965184, "vms": 600485888, "shared": 9043968, "text": 20971520, "lib": 0, "data": 567226368, "dirty": 0, "uss": 31612928, "pss": 31628288, "swap": 0}, "connections": [], "nice": 0, "open_files": 1, "NPROC": "1", "HOSTNAME": "sh-01-09.int", "MAXMEMORY": "8", "SECONDS": "1"}, {"io_counters": {"read_count": 13838, "write_count": 8208, "read_bytes": 44830720, "write_bytes": 163229696, "read_chars": 135161934, "write_chars": 154135771}, "pid": 16364, "status": "sleeping", "cpu_num": 15, "num_fds": 5, "ionice": {"ioclass": "IOPRIO_CLASS_NONE", "value": 4}, "exe": "/usr/bin/singularity", "ppid": 16360, "cpu_affinity": [15], "cmdline": ["singularity", "pull", "--force", "docker://nginx"], "gids": {"real": 32264, "effetive": 32264, "saved": 32264}, "create_time": 1558213399.68, "name": "singularity", "cpu_percent": 0.0, "uids": {"real": 9182, "effetive": 9182, "saved": 9182}, "num_ctx_switches": {"voluntary": 43, "involuntary": 43}, "num_threads": 8, "cwd": "/scratch/users/vsochat", "cpu_times": {"user": 2.25, "system": 0.35, "children_user": 0.0, "children_system": 0.0}, "username": "vsochat", "memory_percent": 0.047472560628798524, "memory_full_info": {"rss": 31965184, "vms": 600485888, "shared": 9043968, "text": 20971520, "lib": 0, "data": 567226368, "dirty": 0, "uss": 31723520, "pss": 31738880, "swap": 0}, "connections": [], "nice": 0, "open_files": 0, "NPROC": "1", "HOSTNAME": "sh-01-09.int", "MAXMEMORY": "8", "SECONDS": "1"}, {"io_counters": {"read_count": 13838, "write_count": 8208, "read_bytes": 44830720, "write_bytes": 163229696, "read_chars": 135161934, "write_chars": 154135771}, "pid": 16364, "status": "sleeping", "cpu_num": 15, "num_fds": 5, "ionice": {"ioclass": "IOPRIO_CLASS_NONE", "value": 4}, "exe": "/usr/bin/singularity", "ppid": 16360, "cpu_affinity": [15], "cmdline": ["singularity", "pull", "--force", "docker://nginx"], "gids": {"real": 32264, "effetive": 32264, "saved": 32264}, "create_time": 1558213399.68, "name": "singularity", "cpu_percent": 0.0, "uids": {"real": 9182, "effetive": 9182, "saved": 9182}, "num_ctx_switches": {"voluntary": 43, "involuntary": 43}, "num_threads": 8, "cwd": "/scratch/users/vsochat", "cpu_times": {"user": 2.25, "system": 0.35, "children_user": 0.0, "children_system": 0.0}, "username": "vsochat", "memory_percent": 0.047472560628798524, "memory_full_info": {"rss": 31965184, "vms": 600485888, "shared": 9043968, "text": 20971520, "lib": 0, "data": 567226368, "dirty": 0, "uss": 31723520, "pss": 31738880, "swap": 0}, "connections": [], "nice": 0, "open_files": 0, "NPROC": "1", "HOSTNAME": "sh-01-09.int", "MAXMEMORY": "8", "SECONDS": "1"}, {"io_counters": {"read_count": 13838, "write_count": 8208, "read_bytes": 44830720, "write_bytes": 163229696, "read_chars": 135161934, "write_chars": 154135771}, "pid": 16364, "status": "sleeping", "cpu_num": 15, "num_fds": 5, "ionice": {"ioclass": "IOPRIO_CLASS_NONE", "value": 4}, "exe": "/usr/bin/singularity", "ppid": 16360, "cpu_affinity": [15], "cmdline": ["singularity", "pull", "--force", "docker://nginx"], "gids": {"real": 32264, "effetive": 32264, "saved": 32264}, "create_time": 1558213399.68, "name": "singularity", "cpu_percent": 0.0, "uids": {"real": 9182, "effetive": 9182, "saved": 9182}, "num_ctx_switches": {"voluntary": 43, "involuntary": 43}, "num_threads": 8, "cwd": "/scratch/users/vsochat", "cpu_times": {"user": 2.25, "system": 0.35, "children_user": 0.0, "children_system": 0.0}, "username": "vsochat", "memory_percent": 0.047472560628798524, "memory_full_info": {"rss": 31965184, "vms": 600485888, "shared": 9043968, "text": 20971520, "lib": 0, "data": 567226368, "dirty": 0, "uss": 31723520, "pss": 31738880, "swap": 0}, "connections": [], "nice": 0, "open_files": 0, "NPROC": "1", "HOSTNAME": "sh-01-09.int", "MAXMEMORY": "8", "SECONDS": "1"}, {"io_counters": {"read_count": 13838, "write_count": 8208, "read_bytes": 44830720, "write_bytes": 163229696, "read_chars": 135161934, "write_chars": 154135771}, "pid": 16364, "status": "sleeping", "cpu_num": 15, "num_fds": 5, "ionice": {"ioclass": "IOPRIO_CLASS_NONE", "value": 4}, "exe": "/usr/bin/singularity", "ppid": 16360, "cpu_affinity": [15], "cmdline": ["singularity", "pull", "--force", "docker://nginx"], "gids": {"real": 32264, "effetive": 32264, "saved": 32264}, "create_time": 1558213399.68, "name": "singularity", "cpu_percent": 0.0, "uids": {"real": 9182, "effetive": 9182, "saved": 9182}, "num_ctx_switches": {"voluntary": 43, "involuntary": 43}, "num_threads": 8, "cwd": "/scratch/users/vsochat", "cpu_times": {"user": 2.25, "system": 0.35, "children_user": 0.0, "children_system": 0.0}, "username": "vsochat", "memory_percent": 0.047472560628798524, "memory_full_info": {"rss": 31965184, "vms": 600485888, "shared": 9043968, "text": 20971520, "lib": 0, "data": 567226368, "dirty": 0, "uss": 31723520, "pss": 31738880, "swap": 0}, "connections": [], "nice": 0, "open_files": 0, "NPROC": "1", "HOSTNAME": "sh-01-09.int", "MAXMEMORY": "8", "SECONDS": "1"}, {"io_counters": {"read_count": 13838, "write_count": 8208, "read_bytes": 44830720, "write_bytes": 163229696, "read_chars": 135161934, "write_chars": 154135771}, "pid": 16364, "status": "sleeping", "cpu_num": 15, "num_fds": 5, "ionice": {"ioclass": "IOPRIO_CLASS_NONE", "value": 4}, "exe": "/usr/bin/singularity", "ppid": 16360, "cpu_affinity": [15], "cmdline": ["singularity", "pull", "--force", "docker://nginx"], "gids": {"real": 32264, "effetive": 32264, "saved": 32264}, "create_time": 1558213399.68, "name": "singularity", "cpu_percent": 0.0, "uids": {"real": 9182, "effetive": 9182, "saved": 9182}, "num_ctx_switches": {"voluntary": 43, "involuntary": 43}, "num_threads": 8, "cwd": "/scratch/users/vsochat", "cpu_times": {"user": 2.25, "system": 0.35, "children_user": 0.0, "children_system": 0.0}, "username": "vsochat", "memory_percent": 0.047472560628798524, "memory_full_info": {"rss": 31965184, "vms": 600485888, "shared": 9043968, "text": 20971520, "lib": 0, "data": 567226368, "dirty": 0, "uss": 31723520, "pss": 31738880, "swap": 0}, "connections": [], "nice": 0, "open_files": 0, "NPROC": "1", "HOSTNAME": "sh-01-09.int", "MAXMEMORY": "8", "SECONDS": "1"}, {"io_counters": {"read_count": 13838, "write_count": 8208, "read_bytes": 44830720, "write_bytes": 163229696, "read_chars": 135161934, "write_chars": 154135771}, "pid": 16364, "status": "sleeping", "cpu_num": 15, "num_fds": 5, "ionice": {"ioclass": "IOPRIO_CLASS_NONE", "value": 4}, "exe": "/usr/bin/singularity", "ppid": 16360, "cpu_affinity": [15], "cmdline": ["singularity", "pull", "--force", "docker://nginx"], "gids": {"real": 32264, "effetive": 32264, "saved": 32264}, "create_time": 1558213399.68, "name": "singularity", "cpu_percent": 0.0, "uids": {"real": 9182, "effetive": 9182, "saved": 9182}, "num_ctx_switches": {"voluntary": 43, "involuntary": 43}, "num_threads": 8, "cwd": "/scratch/users/vsochat", "cpu_times": {"user": 2.25, "system": 0.35, "children_user": 0.0, "children_system": 0.0}, "username": "vsochat", "memory_percent": 0.047472560628798524, "memory_full_info": {"rss": 31965184, "vms": 600485888, "shared": 9043968, "text": 20971520, "lib": 0, "data": 567226368, "dirty": 0, "uss": 31723520, "pss": 31738880, "swap": 0}, "connections": [], "nice": 0, "open_files": 0, "NPROC": "1", "HOSTNAME": "sh-01-09.int", "MAXMEMORY": "8", "SECONDS": "1"}, {"io_counters": {"read_count": 13838, "write_count": 8208, "read_bytes": 44830720, "write_bytes": 163229696, "read_chars": 135161934, "write_chars": 154135771}, "pid": 16364, "status": "sleeping", "cpu_num": 15, "num_fds": 5, "ionice": {"ioclass": "IOPRIO_CLASS_NONE", "value": 4}, "exe": "/usr/bin/singularity", "ppid": 16360, "cpu_affinity": [15], "cmdline": ["singularity", "pull", "--force", "docker://nginx"], "gids": {"real": 32264, "effetive": 32264, "saved": 32264}, "create_time": 1558213399.68, "name": "singularity", "cpu_percent": 0.0, "uids": {"real": 9182, "effetive": 9182, "saved": 9182}, "num_ctx_switches": {"voluntary": 43, "involuntary": 43}, "num_threads": 8, "cwd": "/scratch/users/vsochat", "cpu_times": {"user": 2.25, "system": 0.35, "children_user": 0.0, "children_system": 0.0}, "username": "vsochat", "memory_percent": 0.047472560628798524, "memory_full_info": {"rss": 31965184, "vms": 600485888, "shared": 9043968, "text": 20971520, "lib": 0, "data": 567226368, "dirty": 0, "uss": 31723520, "pss": 31738880, "swap": 0}, "connections": [], "nice": 0, "open_files": 0, "NPROC": "1", "HOSTNAME": "sh-01-09.int", "MAXMEMORY": "8", "SECONDS": "1"}, {"io_counters": {"read_count": 13838, "write_count": 8208, "read_bytes": 44830720, "write_bytes": 163229696, "read_chars": 135161934, "write_chars": 154135771}, "pid": 16364, "status": "sleeping", "cpu_num": 15, "num_fds": 5, "ionice": {"ioclass": "IOPRIO_CLASS_NONE", "value": 4}, "exe": "/usr/bin/singularity", "ppid": 16360, "cpu_affinity": [15], "cmdline": ["singularity", "pull", "--force", "docker://nginx"], "gids": {"real": 32264, "effetive": 32264, "saved": 32264}, "create_time": 1558213399.68, "name": "singularity", "cpu_percent": 0.0, "uids": {"real": 9182, "effetive": 9182, "saved": 9182}, "num_ctx_switches": {"voluntary": 43, "involuntary": 43}, "num_threads": 8, "cwd": "/scratch/users/vsochat", "cpu_times": {"user": 2.25, "system": 0.35, "children_user": 0.0, "children_system": 0.0}, "username": "vsochat", "memory_percent": 0.047472560628798524, "memory_full_info": {"rss": 31965184, "vms": 600485888, "shared": 9043968, "text": 20971520, "lib": 0, "data": 567226368, "dirty": 0, "uss": 31723520, "pss": 31738880, "swap": 0}, "connections": [], "nice": 0, "open_files": 0, "NPROC": "1", "HOSTNAME": "sh-01-09.int", "MAXMEMORY": "8", "SECONDS": "1"}, {"io_counters": {"read_count": 13838, "write_count": 8208, "read_bytes": 44830720, "write_bytes": 163229696, "read_chars": 135161934, "write_chars": 154135771}, "pid": 16364, "status": "sleeping", "cpu_num": 15, "num_fds": 5, "ionice": {"ioclass": "IOPRIO_CLASS_NONE", "value": 4}, "exe": "/usr/bin/singularity", "ppid": 16360, "cpu_affinity": [15], "cmdline": ["singularity", "pull", "--force", "docker://nginx"], "gids": {"real": 32264, "effetive": 32264, "saved": 32264}, "create_time": 1558213399.68, "name": "singularity", "cpu_percent": 0.0, "uids": {"real": 9182, "effetive": 9182, "saved": 9182}, "num_ctx_switches": {"voluntary": 43, "involuntary": 43}, "num_threads": 8, "cwd": "/scratch/users/vsochat", "cpu_times": {"user": 2.25, "system": 0.35, "children_user": 0.0, "children_system": 0.0}, "username": "vsochat", "memory_percent": 0.047472560628798524, "memory_full_info": {"rss": 31965184, "vms": 600485888, "shared": 9043968, "text": 20971520, "lib": 0, "data": 567226368, "dirty": 0, "uss": 31723520, "pss": 31738880, "swap": 0}, "connections": [], "nice": 0, "open_files": 0, "NPROC": "1", "HOSTNAME": "sh-01-09.int", "MAXMEMORY": "8", "SECONDS": "1"}, {"io_counters": {"read_count": 13838, "write_count": 8208, "read_bytes": 44830720, "write_bytes": 163229696, "read_chars": 135161934, "write_chars": 154135771}, "pid": 16364, "status": "sleeping", "cpu_num": 15, "num_fds": 5, "ionice": {"ioclass": "IOPRIO_CLASS_NONE", "value": 4}, "exe": "/usr/bin/singularity", "ppid": 16360, "cpu_affinity": [15], "cmdline": ["singularity", "pull", "--force", "docker://nginx"], "gids": {"real": 32264, "effetive": 32264, "saved": 32264}, "create_time": 1558213399.68, "name": "singularity", "cpu_percent": 0.0, "uids": {"real": 9182, "effetive": 9182, "saved": 9182}, "num_ctx_switches": {"voluntary": 43, "involuntary": 43}, "num_threads": 8, "cwd": "/scratch/users/vsochat", "cpu_times": {"user": 2.25, "system": 0.35, "children_user": 0.0, "children_system": 0.0}, "username": "vsochat", "memory_percent": 0.047472560628798524, "memory_full_info": {"rss": 31965184, "vms": 600485888, "shared": 9043968, "text": 20971520, "lib": 0, "data": 567226368, "dirty": 0, "uss": 31723520, "pss": 31738880, "swap": 0}, "connections": [], "nice": 0, "open_files": 0, "NPROC": "1", "HOSTNAME": "sh-01-09.int", "MAXMEMORY": "8", "SECONDS": "1"}, {"io_counters": {"read_count": 13838, "write_count": 8208, "read_bytes": 44830720, "write_bytes": 163229696, "read_chars": 135161934, "write_chars": 154135771}, "pid": 16364, "status": "sleeping", "cpu_num": 15, "num_fds": 5, "ionice": {"ioclass": "IOPRIO_CLASS_NONE", "value": 4}, "exe": "/usr/bin/singularity", "ppid": 16360, "cpu_affinity": [15], "cmdline": ["singularity", "pull", "--force", "docker://nginx"], "gids": {"real": 32264, "effetive": 32264, "saved": 32264}, "create_time": 1558213399.68, "name": "singularity", "cpu_percent": 0.0, "uids": {"real": 9182, "effetive": 9182, "saved": 9182}, "num_ctx_switches": {"voluntary": 43, "involuntary": 43}, "num_threads": 8, "cwd": "/scratch/users/vsochat", "cpu_times": {"user": 2.25, "system": 0.35, "children_user": 0.0, "children_system": 0.0}, "username": "vsochat", "memory_percent": 0.047472560628798524, "memory_full_info": {"rss": 31965184, "vms": 600485888, "shared": 9043968, "text": 20971520, "lib": 0, "data": 567226368, "dirty": 0, "uss": 31723520, "pss": 31738880, "swap": 0}, "connections": [], "nice": 0, "open_files": 0, "NPROC": "1", "HOSTNAME": "sh-01-09.int", "MAXMEMORY": "8", "SECONDS": "1"}, {"io_counters": {"read_count": 13838, "write_count": 8208, "read_bytes": 44830720, "write_bytes": 163229696, "read_chars": 135161934, "write_chars": 154135771}, "pid": 16364, "status": "sleeping", "cpu_num": 15, "num_fds": 5, "ionice": {"ioclass": "IOPRIO_CLASS_NONE", "value": 4}, "exe": "/usr/bin/singularity", "ppid": 16360, "cpu_affinity": [15], "cmdline": ["singularity", "pull", "--force", "docker://nginx"], "gids": {"real": 32264, "effetive": 32264, "saved": 32264}, "create_time": 1558213399.68, "name": "singularity", "cpu_percent": 0.0, "uids": {"real": 9182, "effetive": 9182, "saved": 9182}, "num_ctx_switches": {"voluntary": 43, "involuntary": 43}, "num_threads": 8, "cwd": "/scratch/users/vsochat", "cpu_times": {"user": 2.25, "system": 0.35, "children_user": 0.0, "children_system": 0.0}, "username": "vsochat", "memory_percent": 0.047472560628798524, "memory_full_info": {"rss": 31965184, "vms": 600485888, "shared": 9043968, "text": 20971520, "lib": 0, "data": 567226368, "dirty": 0, "uss": 31723520, "pss": 31738880, "swap": 0}, "connections": [], "nice": 0, "open_files": 0, "NPROC": "1", "HOSTNAME": "sh-01-09.int", "MAXMEMORY": "8", "SECONDS": "1"}, {"io_counters": {"read_count": 13838, "write_count": 8208, "read_bytes": 44830720, "write_bytes": 163229696, "read_chars": 135161934, "write_chars": 154135771}, "pid": 16364, "status": "sleeping", "cpu_num": 15, "num_fds": 5, "ionice": {"ioclass": "IOPRIO_CLASS_NONE", "value": 4}, "exe": "/usr/bin/singularity", "ppid": 16360, "cpu_affinity": [15], "cmdline": ["singularity", "pull", "--force", "docker://nginx"], "gids": {"real": 32264, "effetive": 32264, "saved": 32264}, "create_time": 1558213399.68, "name": "singularity", "cpu_percent": 0.0, "uids": {"real": 9182, "effetive": 9182, "saved": 9182}, "num_ctx_switches": {"voluntary": 43, "involuntary": 43}, "num_threads": 8, "cwd": "/scratch/users/vsochat", "cpu_times": {"user": 2.25, "system": 0.35, "children_user": 0.0, "children_system": 0.0}, "username": "vsochat", "memory_percent": 0.047472560628798524, "memory_full_info": {"rss": 31965184, "vms": 600485888, "shared": 9043968, "text": 20971520, "lib": 0, "data": 567226368, "dirty": 0, "uss": 31723520, "pss": 31738880, "swap": 0}, "connections": [], "nice": 0, "open_files": 0, "NPROC": "1", "HOSTNAME": "sh-01-09.int", "MAXMEMORY": "8", "SECONDS": "1"}, {"io_counters": {"read_count": 13838, "write_count": 8208, "read_bytes": 44830720, "write_bytes": 163229696, "read_chars": 135161934, "write_chars": 154135771}, "pid": 16364, "status": "sleeping", "cpu_num": 15, "num_fds": 5, "ionice": {"ioclass": "IOPRIO_CLASS_NONE", "value": 4}, "exe": "/usr/bin/singularity", "ppid": 16360, "cpu_affinity": [15], "cmdline": ["singularity", "pull", "--force", "docker://nginx"], "gids": {"real": 32264, "effetive": 32264, "saved": 32264}, "create_time": 1558213399.68, "name": "singularity", "cpu_percent": 0.0, "uids": {"real": 9182, "effetive": 9182, "saved": 9182}, "num_ctx_switches": {"voluntary": 43, "involuntary": 43}, "num_threads": 8, "cwd": "/scratch/users/vsochat", "cpu_times": {"user": 2.25, "system": 0.35, "children_user": 0.0, "children_system": 0.0}, "username": "vsochat", "memory_percent": 0.047472560628798524, "memory_full_info": {"rss": 31965184, "vms": 600485888, "shared": 9043968, "text": 20971520, "lib": 0, "data": 567226368, "dirty": 0, "uss": 31723520, "pss": 31738880, "swap": 0}, "connections": [], "nice": 0, "open_files": 0, "NPROC": "1", "HOSTNAME": "sh-01-09.int", "MAXMEMORY": "8", "SECONDS": "1"}, {"io_counters": {"read_count": 13838, "write_count": 8208, "read_bytes": 44830720, "write_bytes": 163229696, "read_chars": 135161934, "write_chars": 154135771}, "pid": 16364, "status": "sleeping", "cpu_num": 15, "num_fds": 5, "ionice": {"ioclass": "IOPRIO_CLASS_NONE", "value": 4}, "exe": "/usr/bin/singularity", "ppid": 16360, "cpu_affinity": [15], "cmdline": ["singularity", "pull", "--force", "docker://nginx"], "gids": {"real": 32264, "effetive": 32264, "saved": 32264}, "create_time": 1558213399.68, "name": "singularity", "cpu_percent": 0.0, "uids": {"real": 9182, "effetive": 9182, "saved": 9182}, "num_ctx_switches": {"voluntary": 43, "involuntary": 43}, "num_threads": 8, "cwd": "/scratch/users/vsochat", "cpu_times": {"user": 2.25, "system": 0.35, "children_user": 0.0, "children_system": 0.0}, "username": "vsochat", "memory_percent": 0.047472560628798524, "memory_full_info": {"rss": 31965184, "vms": 600485888, "shared": 9043968, "text": 20971520, "lib": 0, "data": 567226368, "dirty": 0, "uss": 31723520, "pss": 31738880, "swap": 0}, "connections": [], "nice": 0, "open_files": 0, "NPROC": "1", "HOSTNAME": "sh-01-09.int", "MAXMEMORY": "8", "SECONDS": "1"}, {"io_counters": {"read_count": 13838, "write_count": 8208, "read_bytes": 44830720, "write_bytes": 163229696, "read_chars": 135161934, "write_chars": 154135771}, "pid": 16364, "status": "sleeping", "cpu_num": 15, "num_fds": 5, "ionice": {"ioclass": "IOPRIO_CLASS_NONE", "value": 4}, "exe": "/usr/bin/singularity", "ppid": 16360, "cpu_affinity": [15], "cmdline": ["singularity", "pull", "--force", "docker://nginx"], "gids": {"real": 32264, "effetive": 32264, "saved": 32264}, "create_time": 1558213399.68, "name": "singularity", "cpu_percent": 0.0, "uids": {"real": 9182, "effetive": 9182, "saved": 9182}, "num_ctx_switches": {"voluntary": 43, "involuntary": 43}, "num_threads": 8, "cwd": "/scratch/users/vsochat", "cpu_times": {"user": 2.25, "system": 0.35, "children_user": 0.0, "children_system": 0.0}, "username": "vsochat", "memory_percent": 0.047472560628798524, "memory_full_info": {"rss": 31965184, "vms": 600485888, "shared": 9043968, "text": 20971520, "lib": 0, "data": 567226368, "dirty": 0, "uss": 31723520, "pss": 31738880, "swap": 0}, "connections": [], "nice": 0, "open_files": 0, "NPROC": "1", "HOSTNAME": "sh-01-09.int", "MAXMEMORY": "8", "SECONDS": "1"}, {"io_counters": {"read_count": 13838, "write_count": 8208, "read_bytes": 44830720, "write_bytes": 163229696, "read_chars": 135161934, "write_chars": 154135771}, "pid": 16364, "status": "sleeping", "cpu_num": 15, "num_fds": 5, "ionice": {"ioclass": "IOPRIO_CLASS_NONE", "value": 4}, "exe": "/usr/bin/singularity", "ppid": 16360, "cpu_affinity": [15], "cmdline": ["singularity", "pull", "--force", "docker://nginx"], "gids": {"real": 32264, "effetive": 32264, "saved": 32264}, "create_time": 1558213399.68, "name": "singularity", "cpu_percent": 0.0, "uids": {"real": 9182, "effetive": 9182, "saved": 9182}, "num_ctx_switches": {"voluntary": 43, "involuntary": 43}, "num_threads": 8, "cwd": "/scratch/users/vsochat", "cpu_times": {"user": 2.25, "system": 0.35, "children_user": 0.0, "children_system": 0.0}, "username": "vsochat", "memory_percent": 0.047472560628798524, "memory_full_info": {"rss": 31965184, "vms": 600485888, "shared": 9043968, "text": 20971520, "lib": 0, "data": 567226368, "dirty": 0, "uss": 31723520, "pss": 31738880, "swap": 0}, "connections": [], "nice": 0, "open_files": 0, "NPROC": "1", "HOSTNAME": "sh-01-09.int", "MAXMEMORY": "8", "SECONDS": "1"}, {"io_counters": {"read_count": 22238, "write_count": 10063, "read_bytes": 44830720, "write_bytes": 206077952, "read_chars": 273222056, "write_chars": 227164739}, "pid": 16364, "status": "sleeping", "cpu_num": 15, "num_fds": 6, "ionice": {"ioclass": "IOPRIO_CLASS_NONE", "value": 4}, "exe": "/usr/bin/singularity", "ppid": 16360, "cpu_affinity": [15], "cmdline": ["singularity", "pull", "--force", "docker://nginx"], "gids": {"real": 32264, "effetive": 32264, "saved": 32264}, "create_time": 1558213399.68, "name": "singularity", "cpu_percent": 0.0, "uids": {"real": 9182, "effetive": 9182, "saved": 9182}, "num_ctx_switches": {"voluntary": 43, "involuntary": 43}, "num_threads": 8, "cwd": "/scratch/users/vsochat", "cpu_times": {"user": 2.26, "system": 0.41, "children_user": 17.4, "children_system": 0.16}, "username": "vsochat", "memory_percent": 0.047472560628798524, "memory_full_info": {"rss": 31965184, "vms": 600485888, "shared": 9043968, "text": 20971520, "lib": 0, "data": 567226368, "dirty": 0, "uss": 31776768, "pss": 31792128, "swap": 0}, "connections": [], "nice": 0, "open_files": 2, "NPROC": "1", "HOSTNAME": "sh-01-09.int", "MAXMEMORY": "8", "SECONDS": "1"}]
